a_selenium_some_js/LICENSE
a_selenium_some_js/README.MD
a_selenium_some_js/__init__.py
a_selenium_some_js/requirements.txt
a_selenium_some_js/thirdparty.json
a_selenium_some_js-0.10.dist-info/LICENSE.rst
a_selenium_some_js-0.10.dist-info/METADATA
a_selenium_some_js-0.10.dist-info/WHEEL
a_selenium_some_js-0.10.dist-info/top_level.txt
a_selenium_some_js-0.10.dist-info/RECORD
